<?xml version="1.0" encoding="UTF-8"?>
<jobform jobcode="CAM31_IDE" jobname="CAM31_IDE" display-name="Custom direction notification">
  <meta_info format_Version="1.0" revision="0000" friday="VAD8000.xml" item_attr_edit="False" />
  <friday href="VAD8000.xml" revision="0000" />
  <iteminfo>
    <item id="ICN" name="Declaration No." input_output="-" required="C" attribute="I" figure="12" form="" order="1" check_attribute="*" check_full="" choice_table="" out_flg="1" in_flg="0" />
    <item id="JKN" name="Classification of outputting corrected report" input_output="-" required="C" attribute="A" figure="1" form="" order="2" check_attribute="*" check_full="" choice_table="" out_flg="1" in_flg="0" />
    <item id="FIC" name="First declaration No." input_output="-" required="C" attribute="A" figure="12" form="" order="3" check_attribute="*" check_full="" choice_table="" out_flg="1" in_flg="0" />
    <item id="BNO" name="Branch number of divided Declaration" input_output="-" required="C" attribute="I" figure="2" form="" order="4" check_attribute="*" check_full="" choice_table="" out_flg="1" in_flg="0" />
    <item id="DNO" name="Number of divisions of divided Declaration" input_output="-" required="C" attribute="I" figure="2" form="" order="5" check_attribute="*" check_full="" choice_table="" out_flg="1" in_flg="0" />
    <item id="TDN" name="Declaration No. of Tentative import export declaration" input_output="-" required="C" attribute="I" figure="12" form="" order="6" check_attribute="*" check_full="" choice_table="" out_flg="1" in_flg="0" />
    <item id="A06" name="Inspection Kind Classification Code" input_output="-" required="C" attribute="A" figure="3" form="" order="7" check_attribute="*" check_full="" choice_table="" out_flg="1" in_flg="0" />
    <item id="A02" name="Declaration Kind Code" input_output="-" required="C" attribute="A" figure="3" form="" order="8" check_attribute="*" check_full="" choice_table="" out_flg="1" in_flg="0" />
    <item id="ADA" name="Cargo classification code" input_output="-" required="C" attribute="A" figure="1" form="" order="9" check_attribute="*" check_full="" choice_table="" out_flg="1" in_flg="0" />
    <item id="ADB" name="Means of transportation code" input_output="-" required="C" attribute="A" figure="1" form="" order="10" check_attribute="*" check_full="" choice_table="" out_flg="1" in_flg="0" />
    <item id="A05" name="Classification of Individual/Organization" input_output="-" required="C" attribute="A" figure="1" form="" order="11" check_attribute="*" check_full="" choice_table="" out_flg="1" in_flg="0" />
    <item id="A00" name="Representative tax code" input_output="-" required="C" attribute="A" figure="4" form="" order="12" check_attribute="*" check_full="" choice_table="" out_flg="1" in_flg="0" />
    <item id="A07" name="Customs Office Name" input_output="-" required="C" attribute="A" figure="10" form="" order="13" check_attribute="*" check_full="" choice_table="" out_flg="1" in_flg="0" />
    <item id="A08" name="Customs Sub-section" input_output="-" required="C" attribute="A" figure="2" form="" order="14" check_attribute="*" check_full="" choice_table="" out_flg="1" in_flg="0" />
    <item id="A09" name="Registered date" input_output="-" required="C" attribute="A" figure="8" form="" order="15" check_attribute="*" check_full="" choice_table="" out_flg="1" in_flg="0" />
    <item id="AD1" name="Registered time" input_output="-" required="C" attribute="A" figure="6" form="" order="16" check_attribute="*" check_full="" choice_table="" out_flg="1" in_flg="0" />
    <item id="AD2" name="Registered date of Correction" input_output="-" required="C" attribute="A" figure="8" form="" order="17" check_attribute="*" check_full="" choice_table="" out_flg="1" in_flg="0" />
    <item id="AD3" name="Registered time of Correction" input_output="-" required="C" attribute="A" figure="6" form="" order="18" check_attribute="*" check_full="" choice_table="" out_flg="1" in_flg="0" />
    <item id="RED" name="Time limit of re-export/re-import" input_output="-" required="C" attribute="A" figure="8" form="" order="19" check_attribute="*" check_full="" choice_table="" out_flg="1" in_flg="0" />
    <item id="AAA" name="Sign of time limit over" input_output="-" required="C" attribute="A" figure="1" form="" order="20" check_attribute="*" check_full="" choice_table="" out_flg="1" in_flg="0" />
    <item id="B99" name="Customs instruction classification" input_output="-" required="C" attribute="A" figure="1" form="" order="21" check_attribute="*" check_full="" choice_table="" out_flg="1" in_flg="0" />
    <item id="D01" name="Date of customs instruction" input_output="-" required="C" attribute="A" figure="8" form="" order="22" check_attribute="*" check_full="" choice_table="" out_flg="1" in_flg="0" />
    <item id="T01" name="Case title of customs instruction" input_output="-" required="C" attribute="W" figure="120" form="" order="23" check_attribute="*" check_full="" choice_table="" out_flg="1" in_flg="0" />
    <item id="I01" name="Content of customs instruction" input_output="-" required="C" attribute="W" figure="420" form="" order="24" check_attribute="*" check_full="" choice_table="" out_flg="1" in_flg="0" />
    <item id="D02" name="Date of customs instruction" input_output="-" required="C" attribute="A" figure="8" form="" order="25" check_attribute="*" check_full="" choice_table="" out_flg="1" in_flg="0" />
    <item id="T02" name="Case title of customs instruction" input_output="-" required="C" attribute="W" figure="120" form="" order="26" check_attribute="*" check_full="" choice_table="" out_flg="1" in_flg="0" />
    <item id="I02" name="Content of customs instruction" input_output="-" required="C" attribute="W" figure="420" form="" order="27" check_attribute="*" check_full="" choice_table="" out_flg="1" in_flg="0" />
    <item id="D03" name="Date of customs instruction" input_output="-" required="C" attribute="A" figure="8" form="" order="28" check_attribute="*" check_full="" choice_table="" out_flg="1" in_flg="0" />
    <item id="T03" name="Case title of customs instruction" input_output="-" required="C" attribute="W" figure="120" form="" order="29" check_attribute="*" check_full="" choice_table="" out_flg="1" in_flg="0" />
    <item id="I03" name="Content of customs instruction" input_output="-" required="C" attribute="W" figure="420" form="" order="30" check_attribute="*" check_full="" choice_table="" out_flg="1" in_flg="0" />
    <item id="D04" name="Date of customs instruction" input_output="-" required="C" attribute="A" figure="8" form="" order="31" check_attribute="*" check_full="" choice_table="" out_flg="1" in_flg="0" />
    <item id="T04" name="Case title of customs instruction" input_output="-" required="C" attribute="W" figure="120" form="" order="32" check_attribute="*" check_full="" choice_table="" out_flg="1" in_flg="0" />
    <item id="I04" name="Content of customs instruction" input_output="-" required="C" attribute="W" figure="420" form="" order="33" check_attribute="*" check_full="" choice_table="" out_flg="1" in_flg="0" />
    <item id="D05" name="Date of customs instruction" input_output="-" required="C" attribute="A" figure="8" form="" order="34" check_attribute="*" check_full="" choice_table="" out_flg="1" in_flg="0" />
    <item id="T05" name="Case title of customs instruction" input_output="-" required="C" attribute="W" figure="120" form="" order="35" check_attribute="*" check_full="" choice_table="" out_flg="1" in_flg="0" />
    <item id="I05" name="Content of customs instruction" input_output="-" required="C" attribute="W" figure="420" form="" order="36" check_attribute="*" check_full="" choice_table="" out_flg="1" in_flg="0" />
    <item id="D06" name="Date of customs instruction" input_output="-" required="C" attribute="A" figure="8" form="" order="37" check_attribute="*" check_full="" choice_table="" out_flg="1" in_flg="0" />
    <item id="T06" name="Case title of customs instruction" input_output="-" required="C" attribute="W" figure="120" form="" order="38" check_attribute="*" check_full="" choice_table="" out_flg="1" in_flg="0" />
    <item id="I06" name="Content of customs instruction" input_output="-" required="C" attribute="W" figure="420" form="" order="39" check_attribute="*" check_full="" choice_table="" out_flg="1" in_flg="0" />
    <item id="D07" name="Date of customs instruction" input_output="-" required="C" attribute="A" figure="8" form="" order="40" check_attribute="*" check_full="" choice_table="" out_flg="1" in_flg="0" />
    <item id="T07" name="Case title of customs instruction" input_output="-" required="C" attribute="W" figure="120" form="" order="41" check_attribute="*" check_full="" choice_table="" out_flg="1" in_flg="0" />
    <item id="I07" name="Content of customs instruction" input_output="-" required="C" attribute="W" figure="420" form="" order="42" check_attribute="*" check_full="" choice_table="" out_flg="1" in_flg="0" />
    <item id="D08" name="Date of customs instruction" input_output="-" required="C" attribute="A" figure="8" form="" order="43" check_attribute="*" check_full="" choice_table="" out_flg="1" in_flg="0" />
    <item id="T08" name="Case title of customs instruction" input_output="-" required="C" attribute="W" figure="120" form="" order="44" check_attribute="*" check_full="" choice_table="" out_flg="1" in_flg="0" />
    <item id="I08" name="Content of customs instruction" input_output="-" required="C" attribute="W" figure="420" form="" order="45" check_attribute="*" check_full="" choice_table="" out_flg="1" in_flg="0" />
    <item id="D09" name="Date of customs instruction" input_output="-" required="C" attribute="A" figure="8" form="" order="46" check_attribute="*" check_full="" choice_table="" out_flg="1" in_flg="0" />
    <item id="T09" name="Case title of customs instruction" input_output="-" required="C" attribute="W" figure="120" form="" order="47" check_attribute="*" check_full="" choice_table="" out_flg="1" in_flg="0" />
    <item id="I09" name="Content of customs instruction" input_output="-" required="C" attribute="W" figure="420" form="" order="48" check_attribute="*" check_full="" choice_table="" out_flg="1" in_flg="0" />
    <item id="D10" name="Date of customs instruction" input_output="-" required="C" attribute="A" figure="8" form="" order="49" check_attribute="*" check_full="" choice_table="" out_flg="1" in_flg="0" />
    <item id="T10" name="Case title of customs instruction" input_output="-" required="C" attribute="W" figure="120" form="" order="50" check_attribute="*" check_full="" choice_table="" out_flg="1" in_flg="0" />
    <item id="I10" name="Content of customs instruction" input_output="-" required="C" attribute="W" figure="420" form="" order="51" check_attribute="*" check_full="" choice_table="" out_flg="1" in_flg="0" />
  </iteminfo>
  <layout>
    <page Font="Courier New, 8.25pt" MinOccurs="1">
      <label AutoSize="False" Location="10, 88" Size="79, 18" Font="Tahoma, 8.25pt" Text="Ngày đăng ký" />
      <label AutoSize="False" Location="10, 62" Size="137, 18" Font="Tahoma, 8.25pt" Text="Mã phân loại kiểm tra" />
      <label Location="10, 49" Size="203, 18" Font="Tahoma, 8.25pt" Text="Số tờ khai tạm nhập tái xuất tương ứng" />
      <prttextbox Format="" Location="226, 51" Size="88, 13" BorderStyle="None" Font="Courier New, 8.25pt" attribute="I" check_attribute="*" check_date="" check_full="" check_time="" choice_keyvalue="" figure="12" form="" id="TDN" input_output="-" name="Declaration No. of Tentative import export declaration" order="6" required="C" />
      <prttextbox Format="hh:mm:ss" Location="162, 91" Size="61, 13" BorderStyle="None" Font="Courier New, 8.25pt" attribute="A" check_attribute="*" check_date="" check_full="" check_time="" choice_keyvalue="" figure="6" form="" id="AD1" input_output="-" name="Registered time" order="16" required="C" />
      <prttextbox Format="" Location="226, 77" Size="75, 13" BorderStyle="None" Font="Courier New, 8.25pt" attribute="A" check_attribute="*" check_date="" check_full="" check_time="" choice_keyvalue="" figure="10" form="" id="A07" input_output="-" name="Customs Office Name" order="13" required="C" />
      <prttextbox Format="" Location="166, 110" Size="13, 13" BorderStyle="None" Font="Courier New, 8.25pt" attribute="A" check_attribute="*" check_date="" check_full="" check_time="" choice_keyvalue="" figure="1" form="" id="B99" input_output="-" name="Customs instruction classification" order="21" required="C" />
      <prttextbox Format="dd/MM/yyyy" Location="86, 91" Size="75, 13" BorderStyle="None" Font="Courier New, 8.25pt" attribute="A" check_attribute="*" check_date="" check_full="" check_time="" choice_keyvalue="" figure="8" form="" id="A09" input_output="-" name="Registered date" order="15" required="C" />
      <pagelabel Location="0, 15" Size="718, 16" Font="Tahoma, 12.75pt, style=Bold" Text="Bản chỉ thị sửa đổi của Hải quan" TextAlign="MiddleCenter" PageFormat="PageTitle" />
      <prttextbox Format="" Location="483, 38" Size="20, 13" BorderStyle="None" Font="Courier New, 8.25pt" attribute="I" check_attribute="*" check_date="" check_full="" check_time="" choice_keyvalue="" figure="2" form="" id="DNO" input_output="-" name="Number of divisions of divided Declaration" order="5" required="C" />
      <label AutoSize="False" Location="395, 63" Size="12, 14" Font="Tahoma, 8.25pt" Text="]" />
      <label AutoSize="False" Location="371, 63" Size="12, 14" Font="Tahoma, 8.25pt" Text="[" />
      <label AutoSize="False" Location="436, 62" Size="191, 18" Font="Tahoma, 8.25pt" Text="Mã số hàng hóa đại diện của tờ khai" />
      <prttextbox Format="" Location="313, 64" Size="27, 13" BorderStyle="None" Font="Courier New, 8.25pt" attribute="A" check_attribute="*" check_date="" check_full="" check_time="" choice_keyvalue="" figure="3" form="" id="A02" input_output="-" name="Declaration Kind Code" order="8" required="C" />
      <prttextbox Format="AA A" Location="147, 64" Size="34, 13" BorderStyle="None" Font="Courier New, 8.25pt" attribute="A" check_attribute="*" check_date="" check_full="" check_time="" choice_keyvalue="" figure="3" form="" id="A06" input_output="-" name="Inspection Kind Classification Code" order="7" required="C" />
      <prttextbox Format="" Location="624, 77" Size="20, 13" BorderStyle="None" Font="Courier New, 8.25pt" attribute="A" check_attribute="*" check_date="" check_full="" check_time="" choice_keyvalue="" figure="2" form="" id="A08" input_output="-" name="Customs Sub-section" order="14" required="C" />
      <label AutoSize="False" Location="443, 125" Size="62, 14" Font="Tahoma, 8.25pt" Text="Nội dung" />
      <label AutoSize="False" Location="198, 125" Size="30, 14" Font="Tahoma, 8.25pt" Text="Tên" />
      <label AutoSize="False" Location="24, 521" Size="19, 14" Font="Tahoma, 8.25pt" Text="10" />
      <label AutoSize="False" Location="24, 478" Size="19, 14" Font="Tahoma, 8.25pt" Text="9" />
      <label AutoSize="False" Location="24, 435" Size="19, 14" Font="Tahoma, 8.25pt" Text="8" />
      <label AutoSize="False" Location="24, 393" Size="19, 14" Font="Tahoma, 8.25pt" Text="7" />
      <label AutoSize="False" Location="24, 351" Size="19, 14" Font="Tahoma, 8.25pt" Text="6" />
      <label AutoSize="False" Location="24, 309" Size="19, 14" Font="Tahoma, 8.25pt" Text="5" />
      <label AutoSize="False" Location="24, 267" Size="19, 14" Font="Tahoma, 8.25pt" Text="4" />
      <label AutoSize="False" Location="24, 226" Size="19, 14" Font="Tahoma, 8.25pt" Text="3" />
      <label AutoSize="False" Location="24, 184" Size="19, 14" Font="Tahoma, 8.25pt" Text="2" />
      <label AutoSize="False" Location="24, 142" Size="19, 14" Font="Tahoma, 8.25pt" Text="1" />
      <label AutoSize="False" Location="68, 125" Size="40, 14" Font="Tahoma, 8.25pt" Text="Ngày" />
      <label AutoSize="False" Location="10, 110" Size="160, 15" Font="Tahoma, 8.25pt" Text="Phân loại chỉ thị của Hải quan" />
      <label AutoSize="False" Location="471, 36" Size="17, 16" Font="Tahoma, 8.25pt" Text="/" />
      <label AutoSize="False" Location="438, 38" Size="11, 12" Font="Tahoma, 8.25pt" Text="-" />
      <label AutoSize="False" Location="10, 36" Size="79, 18" Font="Tahoma, 8.25pt" Text="Số tờ khai" />
      <prttextbox Format="" Location="86, 38" Size="88, 13" BorderStyle="None" Font="Courier New, 8.25pt" attribute="I" check_attribute="*" check_date="" check_full="" check_time="" choice_keyvalue="" figure="12" form="" id="ICN" input_output="-" name="Declaration No." order="1" required="C" />
      <label AutoSize="False" Location="485, 88" Size="140, 18" Font="Tahoma, 8.25pt" Text="Thời hạn tái nhập/ tái xuất" />
      <label Location="0, -1" Size="40, 18" Font="Tahoma, 8.25pt" Text="&lt;IMP&gt;" />
      <prttextbox Format="" Location="383, 64" Size="13, 13" BorderStyle="None" Font="Courier New, 8.25pt" attribute="A" check_attribute="*" check_date="" check_full="" check_time="" choice_keyvalue="" figure="1" form="" id="A05" input_output="-" name="Classification of Individual/Organization" order="11" required="C" />
      <prttextbox Format="" Location="624, 64" Size="34, 13" BorderStyle="None" Font="Courier New, 8.25pt" attribute="A" check_attribute="*" check_date="" check_full="" check_time="" choice_keyvalue="" figure="4" form="" id="A00" input_output="-" name="Representative tax code" order="12" required="C" />
      <prttextbox Format="" Location="451, 38" Size="20, 13" BorderStyle="None" Font="Courier New, 8.25pt" attribute="I" check_attribute="*" check_date="" check_full="" check_time="" choice_keyvalue="" figure="2" form="" id="BNO" input_output="-" name="Branch number of divided Declaration" order="4" required="C" />
      <prttextbox Format="" Location="346, 38" Size="88, 13" BorderStyle="None" Font="Courier New, 8.25pt" attribute="A" check_attribute="*" check_date="" check_full="" check_time="" choice_keyvalue="" figure="12" form="" id="FIC" input_output="-" name="First declaration No." order="3" required="C" />
      <prttextbox Format="dd/MM/yyyy" Location="50, 142" Size="75, 13" BorderStyle="None" Font="Courier New, 8.25pt" attribute="A" check_attribute="*" check_date="" check_full="" check_time="" choice_keyvalue="" figure="8" form="" id="D01" input_output="-" name="Date of customs instruction" order="22" required="C" />
      <prttextbox Format="" Multiline="True" Location="140, 142" Size="147, 28" BorderStyle="None" Font="Courier New, 8.25pt" attribute="W" check_attribute="*" check_date="" check_full="" check_time="" choice_keyvalue="" figure="120" form="" id="T01" input_output="-" name="Case title of customs instruction" order="23" required="C" />
      <prttextbox Format="" Multiline="True" Location="293, 142" Size="357, 42" BorderStyle="None" Font="Courier New, 8.25pt" attribute="W" check_attribute="*" check_date="" check_full="" check_time="" choice_keyvalue="" figure="420" form="" id="I01" input_output="-" name="Content of customs instruction" order="24" required="C" />
      <prttextbox Format="dd/MM/yyyy" Location="50, 184" Size="75, 13" BorderStyle="None" Font="Courier New, 8.25pt" attribute="A" check_attribute="*" check_date="" check_full="" check_time="" choice_keyvalue="" figure="8" form="" id="D02" input_output="-" name="Date of customs instruction" order="25" required="C" />
      <prttextbox Format="" Multiline="True" Location="140, 184" Size="147, 28" BorderStyle="None" Font="Courier New, 8.25pt" attribute="W" check_attribute="*" check_date="" check_full="" check_time="" choice_keyvalue="" figure="120" form="" id="T02" input_output="-" name="Case title of customs instruction" order="26" required="C" />
      <prttextbox Format="" Multiline="True" Location="293, 184" Size="357, 42" BorderStyle="None" Font="Courier New, 8.25pt" attribute="W" check_attribute="*" check_date="" check_full="" check_time="" choice_keyvalue="" figure="420" form="" id="I02" input_output="-" name="Content of customs instruction" order="27" required="C" />
      <prttextbox Format="dd/MM/yyyy" Location="50, 226" Size="75, 13" BorderStyle="None" Font="Courier New, 8.25pt" attribute="A" check_attribute="*" check_date="" check_full="" check_time="" choice_keyvalue="" figure="8" form="" id="D03" input_output="-" name="Date of customs instruction" order="28" required="C" />
      <prttextbox Format="" Multiline="True" Location="140, 226" Size="147, 28" BorderStyle="None" Font="Courier New, 8.25pt" attribute="W" check_attribute="*" check_date="" check_full="" check_time="" choice_keyvalue="" figure="120" form="" id="T03" input_output="-" name="Case title of customs instruction" order="29" required="C" />
      <prttextbox Format="" Multiline="True" Location="293, 226" Size="357, 42" BorderStyle="None" Font="Courier New, 8.25pt" attribute="W" check_attribute="*" check_date="" check_full="" check_time="" choice_keyvalue="" figure="420" form="" id="I03" input_output="-" name="Content of customs instruction" order="30" required="C" />
      <prttextbox Format="dd/MM/yyyy" Location="50, 267" Size="75, 13" BorderStyle="None" Font="Courier New, 8.25pt" attribute="A" check_attribute="*" check_date="" check_full="" check_time="" choice_keyvalue="" figure="8" form="" id="D04" input_output="-" name="Date of customs instruction" order="31" required="C" />
      <prttextbox Format="" Multiline="True" Location="140, 267" Size="147, 28" BorderStyle="None" Font="Courier New, 8.25pt" attribute="W" check_attribute="*" check_date="" check_full="" check_time="" choice_keyvalue="" figure="120" form="" id="T04" input_output="-" name="Case title of customs instruction" order="32" required="C" />
      <prttextbox Format="" Multiline="True" Location="293, 267" Size="357, 42" BorderStyle="None" Font="Courier New, 8.25pt" attribute="W" check_attribute="*" check_date="" check_full="" check_time="" choice_keyvalue="" figure="420" form="" id="I04" input_output="-" name="Content of customs instruction" order="33" required="C" />
      <prttextbox Format="dd/MM/yyyy" Location="50, 309" Size="75, 13" BorderStyle="None" Font="Courier New, 8.25pt" attribute="A" check_attribute="*" check_date="" check_full="" check_time="" choice_keyvalue="" figure="8" form="" id="D05" input_output="-" name="Date of customs instruction" order="34" required="C" />
      <prttextbox Format="" Multiline="True" Location="140, 309" Size="147, 28" BorderStyle="None" Font="Courier New, 8.25pt" attribute="W" check_attribute="*" check_date="" check_full="" check_time="" choice_keyvalue="" figure="120" form="" id="T05" input_output="-" name="Case title of customs instruction" order="35" required="C" />
      <prttextbox Format="" Multiline="True" Location="293, 309" Size="357, 42" BorderStyle="None" Font="Courier New, 8.25pt" attribute="W" check_attribute="*" check_date="" check_full="" check_time="" choice_keyvalue="" figure="420" form="" id="I05" input_output="-" name="Content of customs instruction" order="36" required="C" />
      <prttextbox Format="dd/MM/yyyy" Location="50, 351" Size="75, 13" BorderStyle="None" Font="Courier New, 8.25pt" attribute="A" check_attribute="*" check_date="" check_full="" check_time="" choice_keyvalue="" figure="8" form="" id="D06" input_output="-" name="Date of customs instruction" order="37" required="C" />
      <prttextbox Format="" Multiline="True" Location="140, 351" Size="147, 28" BorderStyle="None" Font="Courier New, 8.25pt" attribute="W" check_attribute="*" check_date="" check_full="" check_time="" choice_keyvalue="" figure="120" form="" id="T06" input_output="-" name="Case title of customs instruction" order="38" required="C" />
      <prttextbox Format="" Multiline="True" Location="293, 351" Size="357, 42" BorderStyle="None" Font="Courier New, 8.25pt" attribute="W" check_attribute="*" check_date="" check_full="" check_time="" choice_keyvalue="" figure="420" form="" id="I06" input_output="-" name="Content of customs instruction" order="39" required="C" />
      <prttextbox Format="dd/MM/yyyy" Location="50, 393" Size="75, 13" BorderStyle="None" Font="Courier New, 8.25pt" attribute="A" check_attribute="*" check_date="" check_full="" check_time="" choice_keyvalue="" figure="8" form="" id="D07" input_output="-" name="Date of customs instruction" order="40" required="C" />
      <prttextbox Format="" Multiline="True" Location="140, 393" Size="147, 28" BorderStyle="None" Font="Courier New, 8.25pt" attribute="W" check_attribute="*" check_date="" check_full="" check_time="" choice_keyvalue="" figure="120" form="" id="T07" input_output="-" name="Case title of customs instruction" order="41" required="C" />
      <prttextbox Format="" Multiline="True" Location="293, 393" Size="357, 42" BorderStyle="None" Font="Courier New, 8.25pt" attribute="W" check_attribute="*" check_date="" check_full="" check_time="" choice_keyvalue="" figure="420" form="" id="I07" input_output="-" name="Content of customs instruction" order="42" required="C" />
      <prttextbox Format="dd/MM/yyyy" Location="50, 435" Size="75, 13" BorderStyle="None" Font="Courier New, 8.25pt" attribute="A" check_attribute="*" check_date="" check_full="" check_time="" choice_keyvalue="" figure="8" form="" id="D08" input_output="-" name="Date of customs instruction" order="43" required="C" />
      <prttextbox Format="" Multiline="True" Location="140, 435" Size="147, 28" BorderStyle="None" Font="Courier New, 8.25pt" attribute="W" check_attribute="*" check_date="" check_full="" check_time="" choice_keyvalue="" figure="120" form="" id="T08" input_output="-" name="Case title of customs instruction" order="44" required="C" />
      <prttextbox Format="" Multiline="True" Location="293, 435" Size="357, 42" BorderStyle="None" Font="Courier New, 8.25pt" attribute="W" check_attribute="*" check_date="" check_full="" check_time="" choice_keyvalue="" figure="420" form="" id="I08" input_output="-" name="Content of customs instruction" order="45" required="C" />
      <prttextbox Format="dd/MM/yyyy" Location="50, 478" Size="75, 13" BorderStyle="None" Font="Courier New, 8.25pt" attribute="A" check_attribute="*" check_date="" check_full="" check_time="" choice_keyvalue="" figure="8" form="" id="D09" input_output="-" name="Date of customs instruction" order="46" required="C" />
      <prttextbox Format="" Multiline="True" Location="140, 478" Size="147, 28" BorderStyle="None" Font="Courier New, 8.25pt" attribute="W" check_attribute="*" check_date="" check_full="" check_time="" choice_keyvalue="" figure="120" form="" id="T09" input_output="-" name="Case title of customs instruction" order="47" required="C" />
      <prttextbox Format="" Multiline="True" Location="293, 478" Size="357, 42" BorderStyle="None" Font="Courier New, 8.25pt" attribute="W" check_attribute="*" check_date="" check_full="" check_time="" choice_keyvalue="" figure="420" form="" id="I09" input_output="-" name="Content of customs instruction" order="48" required="C" />
      <prttextbox Format="dd/MM/yyyy" Location="50, 521" Size="75, 13" BorderStyle="None" Font="Courier New, 8.25pt" attribute="A" check_attribute="*" check_date="" check_full="" check_time="" choice_keyvalue="" figure="8" form="" id="D10" input_output="-" name="Date of customs instruction" order="49" required="C" />
      <prttextbox Format="" Multiline="True" Location="140, 521" Size="147, 28" BorderStyle="None" Font="Courier New, 8.25pt" attribute="W" check_attribute="*" check_date="" check_full="" check_time="" choice_keyvalue="" figure="120" form="" id="T10" input_output="-" name="Case title of customs instruction" order="50" required="C" />
      <prttextbox Format="" Multiline="True" Location="293, 521" Size="357, 42" BorderStyle="None" Font="Courier New, 8.25pt" attribute="W" check_attribute="*" check_date="" check_full="" check_time="" choice_keyvalue="" figure="420" form="" id="I10" input_output="-" name="Content of customs instruction" order="51" required="C" />
      <line LineStyle="Center, Black, Solid, 1" Location="0, 106" Size="718, 0" />
      <label AutoSize="False" Location="492, 75" Size="129, 18" Font="Tahoma, 8.25pt" Text="Mã bộ phận xử lý tờ khai" />
      <label Location="226, 88" Size="117, 18" Font="Tahoma, 8.25pt" Text="Ngày thay đổi đăng ký" />
      <prttextbox Format="dd/MM/yyyy" Location="346, 91" Size="75, 13" BorderStyle="None" Font="Courier New, 8.25pt" attribute="A" check_attribute="*" check_date="" check_full="" check_time="" choice_keyvalue="" figure="8" form="" id="AD2" input_output="-" name="Registered date of Correction" order="17" required="C" />
      <prttextbox Format="hh:mm:ss" Location="421, 91" Size="61, 13" BorderStyle="None" Font="Courier New, 8.25pt" attribute="A" check_attribute="*" check_date="" check_full="" check_time="" choice_keyvalue="" figure="6" form="" id="AD3" input_output="-" name="Registered time of Correction" order="18" required="C" />
      <prttextbox Format="" Location="343, 64" Size="13, 13" BorderStyle="None" Font="Courier New, 8.25pt" attribute="A" check_attribute="*" check_date="" check_full="" check_time="" choice_keyvalue="" figure="1" form="" id="ADA" input_output="-" name="Cargo classification code" order="9" required="C" />
      <prttextbox Format="" Location="357, 64" Size="13, 13" BorderStyle="None" Font="Courier New, 8.25pt" attribute="A" check_attribute="*" check_date="" check_full="" check_time="" choice_keyvalue="" figure="1" form="" id="ADB" input_output="-" name="Means of transportation code" order="10" required="C" />
      <label Location="696, 87" Size="8, 18" Font="Tahoma, 8.25pt" Text="-" />
      <label AutoSize="False" Location="226, 36" Size="124, 18" Font="Tahoma, 8.25pt" Text="Số tờ khai đầu tiên" />
      <label AutoSize="False" Location="10, 75" Size="221, 18" Font="Tahoma, 8.25pt" Text="Tên cơ quan Hải quan tiếp nhận tờ khai" />
      <label AutoSize="False" Location="226, 62" Size="87, 18" Font="Tahoma, 8.25pt" Text="Mã loại hình" />
      <prttextbox Format="dd/MM/yyyy" Location="624, 91" Size="75, 13" BorderStyle="None" Font="Courier New, 8.25pt" attribute="A" check_attribute="*" check_date="" check_full="" check_time="" choice_keyvalue="" figure="8" form="" id="RED" input_output="-" name="Time limit of re-export/re-import" order="19" required="C" />
      <prttextbox Format="" Location="705, 91" Size="13, 13" BorderStyle="None" Font="Courier New, 8.25pt" attribute="A" check_attribute="*" check_date="" check_full="" check_time="" choice_keyvalue="" figure="1" form="" id="AAA" input_output="-" name="Sign of time limit over" order="20" required="C" />
    </page>
  </layout>
</jobform>